asmr_toolkit/__init__.py
asmr_toolkit/cli.py
asmr_toolkit/commands/__init__.py
asmr_toolkit/commands/convert.py
asmr_toolkit/core/__init__.py
asmr_toolkit/core/converter.py
asmr_toolkit/utils/__init__.py
asmr_toolkit/utils/ffmpeg.py
asmr_toolkit/utils/logging.py
asmr_toolkit-1.0.10.dist-info/METADATA
asmr_toolkit-1.0.10.dist-info/WHEEL
asmr_toolkit-1.0.10.dist-info/entry_points.txt
asmr_toolkit-1.0.10.dist-info/licenses/LICENSE
asmr_toolkit-1.0.10.dist-info/RECORD
