Metadata-Version: 2.4
Name: asmr-toolkit
Version: 1.0.10
Summary: A modern CLI tool for audio conversion and processing
License: MIT
License-File: LICENSE
Requires-Python: >=3.8
Requires-Dist: click>=8.0.0
Requires-Dist: pydantic>=2.0.0
Requires-Dist: rich>=10.0.0
